{
	"cell_ID": "bigship_hull",
    "name": "Hull",
    "mass": 2000,
    "mesh_loc": "res/ShipParts/Big_Ship/",
    "mesh_cursor": "Hull_Cursor.obj",
	"aabbMin": [-0.5, -0.5, -0.5],
	"aabbMax": [0.5, 0.5, 0.5],
	
	"categories":
	[
		"bigship_all",
		"bigship_hull"
	],
	
    "nodes": 
	[
      {
        "position": [0, 0, 0],
        "direction": 0
      },
      {
        "position": [0, 0, 0],
        "direction": 1
      },
      {
        "position": [0, 0, 0],
        "direction": 2
      },
      {
        "position": [0, 0, 0],
        "direction": 3
      },
      {
        "position": [0, 0, 0],
        "direction": 4
      },
      {
        "position": [0, 0, 0],
        "direction": 5
      }
	],
	
	"physics_box":
	{
		"halfExtends": [1.5, 1.5, 1.5],
		"offset": [0, 0, 0]
	}
}